ppb/__init__.py
ppb/assetlib.py
ppb/assets.py
ppb/buttons.py
ppb/camera.py
ppb/changelib.py
ppb/directions.py
ppb/engine.py
ppb/errors.py
ppb/events.py
ppb/flags.py
ppb/gomlib.py
ppb/keycodes.py
ppb/scenes.py
ppb/sprites.py
ppb/systemslib.py
ppb/testutils.py
ppb/utils.py
ppb/vfs.py
ppb/debug/sdlinfo.py
ppb/features/animation.py
ppb/features/default_sprites.py
ppb/features/loadingscene.py
ppb/features/twophase.py
ppb/systems/__init__.py
ppb/systems/_utils.py
ppb/systems/clocks.py
ppb/systems/inputs.py
ppb/systems/renderer.py
ppb/systems/sdl_utils.py
ppb/systems/sound.py
ppb/systems/text.py
ppb-3.2.0.dist-info/LICENSE.txt
ppb-3.2.0.dist-info/METADATA
ppb-3.2.0.dist-info/WHEEL
ppb-3.2.0.dist-info/top_level.txt
ppb-3.2.0.dist-info/RECORD
