Metadata-Version: 2.1
Name: ppb
Version: 3.2.0
Summary: An Event Driven Python Game Engine
Home-page: https://github.com/ppb/pursuedpybear
Author: Piper Thunstrom
Author-email: pathunstrom@gmail.com
License: Artistic-2.0
Classifier: Development Status :: 4 - Beta
Classifier: Intended Audience :: Education
Classifier: Intended Audience :: Developers
Classifier: License :: OSI Approved :: Artistic License
Classifier: Natural Language :: English
Classifier: Programming Language :: Python :: 3
Classifier: Programming Language :: Python :: 3.8
Classifier: Programming Language :: Python :: 3.9
Classifier: Programming Language :: Python :: 3.10
Classifier: Programming Language :: Python :: 3.11
Classifier: Programming Language :: Python :: 3.12
Classifier: Topic :: Games/Entertainment
Classifier: Topic :: Software Development :: Libraries
Classifier: Operating System :: OS Independent
Requires-Python: >=3.8
License-File: LICENSE.txt
Requires-Dist: PySDL2
Requires-Dist: pysdl2-dll
Requires-Dist: ppb-vector ~=1.0
Requires-Dist: Deprecated ~=1.2.12
